hsreplay/__init__.py
hsreplay/document.py
hsreplay/dumper.py
hsreplay/elements.py
hsreplay/stream.py
hsreplay/utils.py
hsreplay-1.16.2.dist-info/licenses/LICENSE
hsreplay-1.16.2.dist-info/METADATA
hsreplay-1.16.2.dist-info/WHEEL
hsreplay-1.16.2.dist-info/top_level.txt
hsreplay-1.16.2.dist-info/RECORD
