Metadata-Version: 2.4
Name: hsreplay
Version: 1.16.2
Summary: A library for creating and parsing HSReplay files
Home-page: https://github.com/HearthSim/python-hsreplay/
Download-URL: https://github.com/HearthSim/python-hsreplay/tarball/master
Author: Jerome Leclanche
Author-email: jerome@hearthsim.net
Classifier: Development Status :: 5 - Production/Stable
Classifier: Intended Audience :: Developers
Classifier: License :: OSI Approved :: MIT License
Classifier: Programming Language :: Python
Classifier: Programming Language :: Python :: 3
Classifier: Programming Language :: Python :: 3.6
Classifier: Topic :: Games/Entertainment
License-File: LICENSE
Requires-Dist: aniso8601
Requires-Dist: hearthstone
Requires-Dist: hslog>=1.15.1
Requires-Dist: lxml
Dynamic: download-url
Dynamic: license-file
